femail/__init__.py
femail/pepipost/__init__.py
femail-1.0.1.dist-info/LICENSE.MD
femail-1.0.1.dist-info/METADATA
femail-1.0.1.dist-info/WHEEL
femail-1.0.1.dist-info/namespace_packages.txt
femail-1.0.1.dist-info/top_level.txt
femail-1.0.1.dist-info/RECORD
