Metadata-Version: 2.1
Name: femail
Version: 1.0.1
Summary: The python (fe)Mail Client
Home-page: UNKNOWN
Author: CodewarsNL
License: UNKNOWN
Platform: Posix
Requires-Python: >=3.6.*
Requires-Dist: requests
Requires-Dist: jinja2
